Metadata-Version: 2.1
Name: PyImageOrganizer
Version: 1.2
Summary: Sorts images/videos/random files into folders by year, month, date/time
Home-page: https://github.com/jlw4049/PyImageOrganizer
Author: Jessie Wilson
Author-email: jessielw4049@gmail.com
License: MIT
Keywords: PyImageOrganizer
Classifier: Development Status :: 5 - Production/Stable
Classifier: Intended Audience :: Developers
Classifier: Operating System :: Microsoft :: Windows
Classifier: Operating System :: MacOS
Classifier: Operating System :: POSIX :: Linux
Classifier: License :: OSI Approved :: MIT License
Classifier: Programming Language :: Python :: 3
License-File: LICENSE
